zeroshotdata/__init__.py
zeroshotdata/main.py
zeroshotdata-0.2.3.dist-info/METADATA
zeroshotdata-0.2.3.dist-info/WHEEL
zeroshotdata-0.2.3.dist-info/top_level.txt
zeroshotdata-0.2.3.dist-info/RECORD
